apigratis/Service.py
apigratis/__init__.py
apigratis-1.0.0.dist-info/LICENSE
apigratis-1.0.0.dist-info/METADATA
apigratis-1.0.0.dist-info/WHEEL
apigratis-1.0.0.dist-info/top_level.txt
apigratis-1.0.0.dist-info/RECORD
