Metadata-Version: 2.1
Name: apigratis
Version: 1.0.0
Summary: Transforme seus projetos em soluções inteligentes com nossa API. Com recursos como API do WhatsApp, geolocalização, rastreamento de encomendas, verificação de CPF/CNPJ e mais, você pode criar soluções eficientes e funcionais
Home-page: https://github.com/APIBrasil/apigratis-sdk-python
Author: APIBRASIL
Author-email: contato@apibrasil.com.br
License: MIT License
Keywords: whatsapp api,apibrasil,cnpj,sms,cep,consulta,api,brasil,gratis,free,whatsapp,apiwhatsapp,apigratis,apifree
Platform: UNKNOWN
Requires-Dist: requests
